src/seleniumPythonFramework_VeriSoft/__init__.py
src/seleniumPythonFramework_VeriSoft/data/read_data.py
src/seleniumPythonFramework_VeriSoft/drivers/BraveDriver.py
src/seleniumPythonFramework_VeriSoft/drivers/ChromeDriver.py
src/seleniumPythonFramework_VeriSoft/fixtures/CreateTargetDirectory.py
src/seleniumPythonFramework_VeriSoft/fixtures/InitGlobalParameters.py
src/seleniumPythonFramework_VeriSoft/fixtures/Loggers.py
src/seleniumPythonFramework_VeriSoft/fixtures/OpenSiteWithCRXExtension.py
src/seleniumPythonFramework_VeriSoft/fixtures/ParameterInjection.py
src/seleniumPythonFramework_VeriSoft/fixtures/Screenshot.py
src/seleniumPythonFramework_VeriSoft/fixtures/SetupDriver.py
src/seleniumPythonFramework_VeriSoft/fixtures/SetupDriverWithMetamaskExtension.py
src/seleniumPythonFramework_VeriSoft/infra/CustomEventListener.py
src/seleniumPythonFramework_VeriSoft/utils/HTTPMethods.py
src/seleniumPythonFramework_VeriSoft/utils/WalletsActionsInterface.py
src/seleniumPythonFramework_VeriSoft/utils/enum/HTTPStatusCodes.py
src/seleniumPythonFramework_VeriSoft/utils/enum/NetworkTypes.py
src/seleniumPythonFramework_VeriSoft/utils/enum/Wallets.py
dcentralab_qa_automations-0.0.1.dist-info/METADATA
dcentralab_qa_automations-0.0.1.dist-info/WHEEL
dcentralab_qa_automations-0.0.1.dist-info/licenses/LICENSE
dcentralab_qa_automations-0.0.1.dist-info/RECORD
